panel_chemistry/__init__.py
panel_chemistry/bokeh.ext.json
panel_chemistry/index.ts
panel_chemistry/package-lock.json
panel_chemistry/package.json
panel_chemistry/py.typed
panel_chemistry/tsconfig.json
panel_chemistry/bokeh_extensions/__init__.py
panel_chemistry/bokeh_extensions/index.ts
panel_chemistry/bokeh_extensions/jsme_editor.py
panel_chemistry/bokeh_extensions/jsme_editor.ts
panel_chemistry/bokeh_extensions/ngl_viewer.py
panel_chemistry/bokeh_extensions/ngl_viewer.ts
panel_chemistry/dist/panel_chemistry.js
panel_chemistry/dist/panel_chemistry.js.map
panel_chemistry/dist/panel_chemistry.json
panel_chemistry/dist/panel_chemistry.min.js
panel_chemistry/dist/lib/index.d.ts
panel_chemistry/dist/lib/index.js
panel_chemistry/dist/lib/index.js.map
panel_chemistry/dist/lib/bokeh_extensions/index.d.ts
panel_chemistry/dist/lib/bokeh_extensions/index.js
panel_chemistry/dist/lib/bokeh_extensions/index.js.map
panel_chemistry/dist/lib/bokeh_extensions/jsme_editor.d.ts
panel_chemistry/dist/lib/bokeh_extensions/jsme_editor.js
panel_chemistry/dist/lib/bokeh_extensions/jsme_editor.js.map
panel_chemistry/dist/lib/bokeh_extensions/ngl_viewer.d.ts
panel_chemistry/dist/lib/bokeh_extensions/ngl_viewer.js
panel_chemistry/dist/lib/bokeh_extensions/ngl_viewer.js.map
panel_chemistry/pane/__init__.py
panel_chemistry/pane/ngl_viewer.py
panel_chemistry/pane/pdbe_molstar.py
panel_chemistry/pane/py3dmol_viewer.py
panel_chemistry/widgets/__init__.py
panel_chemistry/widgets/jsme_editor.py
panel_chemistry-0.2.2.dist-info/LICENSE
panel_chemistry-0.2.2.dist-info/METADATA
panel_chemistry-0.2.2.dist-info/WHEEL
panel_chemistry-0.2.2.dist-info/top_level.txt
panel_chemistry-0.2.2.dist-info/RECORD
